{
  "rankedAt": "2026-07-17T10:47:30.295Z",
  "lens": "独立報道社数(volume)順",
  "events": [
    {
      "headline": "改正皇室典範が成立　制定７９年で初、養子男性子孫に継承権―女性皇族、家族は一般国民",
      "slug": "改正皇室典範が成立制定年で初養子男性子孫に継承権",
      "time": "2026-07-17T10:34:10.000Z",
      "independentSources": 3,
      "sources": [
        "NHK 主要ニュース",
        "Yahoo!ニュース 主要",
        "時事ドットコム"
      ],
      "count": 7,
      "hasPrimary": false,
      "members": [
        {
          "title": "衆院本会議 今国会の会期 25日まで8日間延長を議決",
          "snippet": "国会の会期末の17日、衆議院本会議では、会期を来週25日まで8日間延長することを、自民・維新両党とチームみらいなどの賛成多数で議決しました。",
          "source": "NHK 主要ニュース",
          "link": "https://news.web.nhk/newsweb/na/na-k10015179431000",
          "ty": "press",
          "linkKind": "article"
        },
        {
          "title": "皇族数確保に向けた改正皇室典範 参議院本会議で可決・成立",
          "snippet": "皇族数の確保に向けて、女性皇族が結婚後も皇室に残ることや、旧皇族の男系男子を養子に迎えられるようにすることを盛り込んだ改正皇室典範は、参議院本会議で採決が行われ、自民・維新両党と国民民主党、公明党、参…",
          "source": "NHK 主要ニュース",
          "link": "https://news.web.nhk/newsweb/na/na-k10015179021000",
          "ty": "press",
          "linkKind": "article"
        },
        {
          "title": "再審制度見直し 改正刑事訴訟法が参議院本会議で可決・成立",
          "snippet": "再審＝裁判のやり直しの制度の見直しをめぐり、再審開始の決定に対する検察による不服申し立てを原則禁止することなどを盛り込んだ改正刑事訴訟法は、参議院本会議で採決が行われ、自民・維新両党と参政党などの賛成…",
          "source": "NHK 主要ニュース",
          "link": "https://news.web.nhk/newsweb/na/na-k10015179011000",
          "ty": "press",
          "linkKind": "article"
        },
        {
          "title": "国旗損壊処罰法 参議院本会議で可決・成立",
          "snippet": "日本の国旗を損壊する行為を罰する法律は、参議院本会議で採決が行われ、自民・維新両党と国民民主党、参政党などの賛成多数で可決・成立しました。日本の国旗を損壊する行為を罰する法律は、自民・維新両党と、国民…",
          "source": "NHK 主要ニュース",
          "link": "https://news.web.nhk/newsweb/na/na-k10015179001000",
          "ty": "press",
          "linkKind": "article"
        },
        {
          "title": "国会会期を8日間延長 25日まで",
          "snippet": "",
          "source": "Yahoo!ニュース 主要",
          "link": "https://news.yahoo.co.jp/pickup/6588315?source=rss",
          "ty": "press",
          "linkKind": "article"
        },
        {
          "title": "国会、２５日まで延長　副首都法案で攻防へ",
          "snippet": "",
          "source": "時事ドットコム",
          "link": "https://www.jiji.com/jc/article?k=2026071700290&g=pol&m=rss",
          "ty": "press",
          "linkKind": "article"
        },
        {
          "title": "改正皇室典範が成立　制定７９年で初、養子男性子孫に継承権―女性皇族、家族は一般国民",
          "snippet": "",
          "source": "時事ドットコム",
          "link": "https://www.jiji.com/jc/article?k=2026071700121&g=pol&m=rss",
          "ty": "press",
          "linkKind": "article"
        }
      ]
    },
    {
      "headline": "関東で猛烈な雨相次ぐ 土砂災害・浸水・氾濫に厳重警戒を",
      "slug": "関東で猛烈な雨相次ぐ土砂災害浸水氾濫に厳重警戒を",
      "time": "2026-07-17T10:46:06.000Z",
      "independentSources": 2,
      "sources": [
        "NHK 主要ニュース",
        "気象庁 気象警報・注意報"
      ],
      "count": 3,
      "hasPrimary": true,
      "members": [
        {
          "title": "関東で猛烈な雨相次ぐ 土砂災害・浸水・氾濫に厳重警戒を",
          "snippet": "湿った空気の影響で、17日は関東を中心に大気の状態が非常に不安定になっていて、午前中から猛烈な雨が相次いで降っています。群馬県太田市では「記録的短時間大雨」の気象防災速報が発表されるなど、関東北部でも…",
          "source": "NHK 主要ニュース",
          "link": "https://news.web.nhk/newsweb/na/na-k10015178661000",
          "ty": "press",
          "linkKind": "article"
        },
        {
          "title": "群馬 太田市 市内の一部地区に避難指示",
          "snippet": "群馬県太田市はレベル4土砂災害危険警報などが発表されたことを受けて午後5時24分に市内の一部の地区に避難指示を出しました。危険な場所から全員避難するよう呼びかけています。",
          "source": "NHK 主要ニュース",
          "link": "https://news.web.nhk/newsweb/na/na-k10015179571000",
          "ty": "press",
          "linkKind": "article"
        },
        {
          "title": "気象警報・注意報（Ｒ０６）（土砂）",
          "snippet": "【埼玉県土砂災害警報・注意報】南部、北部では、土砂災害に注意してください。",
          "source": "気象庁 気象警報・注意報",
          "link": "https://www.data.jma.go.jp/developer/xml/data/20260717104607_0_VPWW56_110000.xml",
          "ty": "prim",
          "linkKind": "data"
        }
      ]
    },
    {
      "headline": "Trump alleges China meddled in 2020 election and questions voting security ahead of midterms",
      "slug": "TrumpallegesChinameddled",
      "time": "2026-07-17T10:10:25.000Z",
      "independentSources": 2,
      "sources": [
        "BBC World",
        "Al Jazeera"
      ],
      "count": 3,
      "hasPrimary": false,
      "members": [
        {
          "title": "Trump alleges China meddled in 2020 election and questions voting security ahead of midterms",
          "snippet": "China said Trump's claims were fabricated and US Democrats said he was paving the way to undermine November's elections.",
          "source": "BBC World",
          "link": "https://www.bbc.co.uk/news/articles/cx2k9wvv5wyo?at_medium=RSS&at_campaign=rss",
          "ty": "press",
          "linkKind": "article"
        },
        {
          "title": "Knesset dissolves: How will Israel vote in October’s general election?",
          "snippet": "Knesset dissolves after first full term since 1988, with Israel heading towards crucial elections on October 27, 2026.",
          "source": "Al Jazeera",
          "link": "https://www.aljazeera.com/news/2026/7/17/knesset-dissolves-how-will-israel-vote-in-octobers-general-election?traffic_source=rss",
          "ty": "press",
          "linkKind": "article"
        },
        {
          "title": "Israel headed for October election as parliament dissolved",
          "snippet": "PM Netanyahu’s political survival at stake as Knesset dissolves before the vote.",
          "source": "Al Jazeera",
          "link": "https://www.aljazeera.com/news/2026/7/17/israel-headed-for-october-election-as-parliament-dissolved?traffic_source=rss",
          "ty": "press",
          "linkKind": "article"
        }
      ]
    },
    {
      "headline": "US launches new strikes as Iran says civilian infrastructure hit",
      "slug": "USlaunchesnewstrikesasIr",
      "time": "2026-07-17T10:14:30.000Z",
      "independentSources": 2,
      "sources": [
        "BBC World",
        "Al Jazeera"
      ],
      "count": 2,
      "hasPrimary": false,
      "members": [
        {
          "title": "US launches new strikes as Iran says civilian infrastructure hit",
          "snippet": "Tehran says the US strikes hit bridges, while the US boards a ship in the Strait of Hormuz.",
          "source": "BBC World",
          "link": "https://www.bbc.co.uk/news/articles/c151gdjwd10o?at_medium=RSS&at_campaign=rss",
          "ty": "press",
          "linkKind": "article"
        },
        {
          "title": "US strikes destroy key bridges, tower in southern Iran",
          "snippet": "US strikes destroy key bridges, tower in southern Iran",
          "source": "Al Jazeera",
          "link": "https://www.aljazeera.com/video/newsfeed/2026/7/17/us-strikes-destroy-key-bridges-tower-in-southern-iran?traffic_source=rss",
          "ty": "press",
          "linkKind": "article"
        }
      ]
    },
    {
      "headline": "気象特別警報・警報・注意報",
      "slug": "気象特別警報警報注意報",
      "time": "2026-07-17T10:33:55.000Z",
      "independentSources": 1,
      "sources": [
        "気象庁 気象警報・注意報"
      ],
      "count": 3,
      "hasPrimary": true,
      "members": [
        {
          "title": "気象特別警報・警報・注意報",
          "snippet": "【青森県気象警報・注意報】青森県では、濃霧による視程障害に注意してください。",
          "source": "気象庁 気象警報・注意報",
          "link": "https://www.data.jma.go.jp/developer/xml/data/20260717103356_0_VPWW53_020000.xml",
          "ty": "prim",
          "linkKind": "data"
        },
        {
          "title": "気象警報・注意報（Ｈ２７）",
          "snippet": "【青森県気象警報・注意報】青森県では、濃霧による視程障害に注意してください。",
          "source": "気象庁 気象警報・注意報",
          "link": "https://www.data.jma.go.jp/developer/xml/data/20260717103356_0_VPWW54_020000.xml",
          "ty": "prim",
          "linkKind": "data"
        },
        {
          "title": "気象特別警報・警報・注意報",
          "snippet": "【青森県気象警報・注意報】津軽、三八上北では、落雷に注意してください。青森県では、濃霧による視程障害に注意してください。",
          "source": "気象庁 気象警報・注意報",
          "link": "https://www.data.jma.go.jp/developer/xml/data/20260717103026_0_VPWW53_020000.xml",
          "ty": "prim",
          "linkKind": "data"
        }
      ]
    },
    {
      "headline": "気象警報・注意報（Ｈ２７）",
      "slug": "気象警報注意報",
      "time": "2026-07-17T10:46:20.000Z",
      "independentSources": 1,
      "sources": [
        "気象庁 気象警報・注意報"
      ],
      "count": 2,
      "hasPrimary": true,
      "members": [
        {
          "title": "気象警報・注意報（Ｈ２７）",
          "snippet": "【埼玉県気象警報・注意報】南部では、低い土地の浸水に警戒してください。",
          "source": "気象庁 気象警報・注意報",
          "link": "https://www.data.jma.go.jp/developer/xml/data/20260717104621_0_VPWW54_110000.xml",
          "ty": "prim",
          "linkKind": "data"
        },
        {
          "title": "気象特別警報・警報・注意報",
          "snippet": "【埼玉県気象警報・注意報】南部では、低い土地の浸水に警戒してください。",
          "source": "気象庁 気象警報・注意報",
          "link": "https://www.data.jma.go.jp/developer/xml/data/20260717104621_0_VPWW53_110000.xml",
          "ty": "prim",
          "linkKind": "data"
        }
      ]
    },
    {
      "headline": "気象警報・注意報（Ｈ２７）",
      "slug": "気象警報注意報",
      "time": "2026-07-17T10:31:30.000Z",
      "independentSources": 1,
      "sources": [
        "気象庁 気象警報・注意報"
      ],
      "count": 2,
      "hasPrimary": true,
      "members": [
        {
          "title": "気象警報・注意報（Ｈ２７）",
          "snippet": "【茨城県気象警報・注意報】南部では、低い土地の浸水に注意してください。茨城県では、落雷や濃霧による視程障害に注意してください。",
          "source": "気象庁 気象警報・注意報",
          "link": "https://www.data.jma.go.jp/developer/xml/data/20260717103131_0_VPWW54_080000.xml",
          "ty": "prim",
          "linkKind": "data"
        },
        {
          "title": "気象特別警報・警報・注意報",
          "snippet": "【茨城県気象警報・注意報】南部では、低い土地の浸水に注意してください。茨城県では、落雷や濃霧による視程障害に注意してください。",
          "source": "気象庁 気象警報・注意報",
          "link": "https://www.data.jma.go.jp/developer/xml/data/20260717103131_0_VPWW53_080000.xml",
          "ty": "prim",
          "linkKind": "data"
        }
      ]
    },
    {
      "headline": "FIFA World Cup: 10 things to know before Spain-Argentina final in New York",
      "slug": "FIFAWorldCup10thingstokn",
      "time": "2026-07-17T09:47:55.000Z",
      "independentSources": 1,
      "sources": [
        "Al Jazeera"
      ],
      "count": 2,
      "hasPrimary": false,
      "members": [
        {
          "title": "FIFA World Cup: 10 things to know before Spain-Argentina final in New York",
          "snippet": "From the viral photo of Lionel Messi with baby Lamine Yamal to Donald Trump&#039;s presence and the NFL-style half-time ",
          "source": "Al Jazeera",
          "link": "https://www.aljazeera.com/sports/2026/7/17/spain-argentina-fifa-world-cup-2026-final-messi-yamal-photo-trump?traffic_source=rss",
          "ty": "press",
          "linkKind": "article"
        },
        {
          "title": "Watch FIFA World Cup: Argentina arrives in New Jersey ahead of Spain final",
          "snippet": "Latest match highlights, reaction and previews from the FIFA World Cup 2026 in North America.",
          "source": "Al Jazeera",
          "link": "https://www.aljazeera.com/video/2026/7/17/video-world-cup-2026-highlights?traffic_source=rss",
          "ty": "press",
          "linkKind": "article"
        }
      ]
    },
    {
      "headline": "鹿児島 霧島 川で男性の遺体見つかる 不明の5歳男児の可能性",
      "slug": "鹿児島霧島川で男性の遺体見つかる不明の5歳男児の",
      "time": "2026-07-17T09:50:29.000Z",
      "independentSources": 1,
      "sources": [
        "NHK 主要ニュース"
      ],
      "count": 1,
      "hasPrimary": false,
      "members": [
        {
          "title": "鹿児島 霧島 川で男性の遺体見つかる 不明の5歳男児の可能性",
          "snippet": "17日午前、鹿児島県霧島市の川から男性の遺体が見つかりました。警察は、先月、近くの温泉施設に家族と訪れたまま行方が分からなくなっている5歳の男の子の可能性もあるとみて、確認を進めています。",
          "source": "NHK 主要ニュース",
          "link": "https://news.web.nhk/newsweb/na/na-k10015178991000",
          "ty": "press",
          "linkKind": "article"
        }
      ]
    },
    {
      "headline": "子のSNSいつから? 禁止の是非",
      "slug": "子のSNSいつから禁止の是非",
      "time": "2026-07-17T07:22:20.000Z",
      "independentSources": 1,
      "sources": [
        "Yahoo!ニュース 主要"
      ],
      "count": 1,
      "hasPrimary": false,
      "members": [
        {
          "title": "子のSNSいつから? 禁止の是非",
          "snippet": "",
          "source": "Yahoo!ニュース 主要",
          "link": "https://news.yahoo.co.jp/pickup/6588282?source=rss",
          "ty": "press",
          "linkKind": "article"
        }
      ]
    },
    {
      "headline": "5歳不明 発見の遺体は身長115cm",
      "slug": "5歳不明発見の遺体は身長115cm",
      "time": "2026-07-17T08:05:37.000Z",
      "independentSources": 1,
      "sources": [
        "Yahoo!ニュース 主要"
      ],
      "count": 1,
      "hasPrimary": false,
      "members": [
        {
          "title": "5歳不明 発見の遺体は身長115cm",
          "snippet": "",
          "source": "Yahoo!ニュース 主要",
          "link": "https://news.yahoo.co.jp/pickup/6588289?source=rss",
          "ty": "press",
          "linkKind": "article"
        }
      ]
    },
    {
      "headline": "台船で女性倒れ死亡 殺人で捜査",
      "slug": "台船で女性倒れ死亡殺人で捜査",
      "time": "2026-07-17T09:38:20.000Z",
      "independentSources": 1,
      "sources": [
        "Yahoo!ニュース 主要"
      ],
      "count": 1,
      "hasPrimary": false,
      "members": [
        {
          "title": "台船で女性倒れ死亡 殺人で捜査",
          "snippet": "",
          "source": "Yahoo!ニュース 主要",
          "link": "https://news.yahoo.co.jp/pickup/6588309?source=rss",
          "ty": "press",
          "linkKind": "article"
        }
      ]
    },
    {
      "headline": "トラック出火 郵便物4600通が焼損",
      "slug": "トラック出火郵便物4600通が焼損",
      "time": "2026-07-17T08:58:02.000Z",
      "independentSources": 1,
      "sources": [
        "Yahoo!ニュース 主要"
      ],
      "count": 1,
      "hasPrimary": false,
      "members": [
        {
          "title": "トラック出火 郵便物4600通が焼損",
          "snippet": "",
          "source": "Yahoo!ニュース 主要",
          "link": "https://news.yahoo.co.jp/pickup/6588301?source=rss",
          "ty": "press",
          "linkKind": "article"
        }
      ]
    },
    {
      "headline": "カープ矢野抹消 週刊誌報道受けて",
      "slug": "カプ矢野抹消週刊誌報道受けて",
      "time": "2026-07-17T08:15:22.000Z",
      "independentSources": 1,
      "sources": [
        "Yahoo!ニュース 主要"
      ],
      "count": 1,
      "hasPrimary": false,
      "members": [
        {
          "title": "カープ矢野抹消 週刊誌報道受けて",
          "snippet": "",
          "source": "Yahoo!ニュース 主要",
          "link": "https://news.yahoo.co.jp/pickup/6588292?source=rss",
          "ty": "press",
          "linkKind": "article"
        }
      ]
    },
    {
      "headline": "松本人志 大腸腫瘍を手術と告白",
      "slug": "松本人志大腸腫瘍を手術と告白",
      "time": "2026-07-17T10:30:27.000Z",
      "independentSources": 1,
      "sources": [
        "Yahoo!ニュース 主要"
      ],
      "count": 1,
      "hasPrimary": false,
      "members": [
        {
          "title": "松本人志 大腸腫瘍を手術と告白",
          "snippet": "",
          "source": "Yahoo!ニュース 主要",
          "link": "https://news.yahoo.co.jp/pickup/6588313?source=rss",
          "ty": "press",
          "linkKind": "article"
        }
      ]
    },
    {
      "headline": "金曜ドラマ もう「今期1番」の声",
      "slug": "金曜ドラマもう今期1番の声",
      "time": "2026-07-17T09:15:13.000Z",
      "independentSources": 1,
      "sources": [
        "Yahoo!ニュース 主要"
      ],
      "count": 1,
      "hasPrimary": false,
      "members": [
        {
          "title": "金曜ドラマ もう「今期1番」の声",
          "snippet": "",
          "source": "Yahoo!ニュース 主要",
          "link": "https://news.yahoo.co.jp/pickup/6588307?source=rss",
          "ty": "press",
          "linkKind": "article"
        }
      ]
    },
    {
      "headline": "キオクシアの特許侵害認定　賠償金３７０億円―米陪審評決",
      "slug": "キオクシアの特許侵害認定賠償金億円米陪審評決",
      "time": "2026-07-17T06:25:00.000Z",
      "independentSources": 1,
      "sources": [
        "時事ドットコム"
      ],
      "count": 1,
      "hasPrimary": false,
      "members": [
        {
          "title": "キオクシアの特許侵害認定　賠償金３７０億円―米陪審評決",
          "snippet": "",
          "source": "時事ドットコム",
          "link": "https://www.jiji.com/jc/article?k=2026071700491&g=int&m=rss",
          "ty": "press",
          "linkKind": "article"
        }
      ]
    },
    {
      "headline": "内閣支持４９％、発足後最低　６０歳代で激減―時事世論調査",
      "slug": "内閣支持発足後最低歳代で激減時事世論調査",
      "time": "2026-07-16T08:03:00.000Z",
      "independentSources": 1,
      "sources": [
        "時事ドットコム"
      ],
      "count": 1,
      "hasPrimary": false,
      "members": [
        {
          "title": "内閣支持４９％、発足後最低　６０歳代で激減―時事世論調査",
          "snippet": "",
          "source": "時事ドットコム",
          "link": "https://www.jiji.com/jc/article?k=2026071600709&g=pol&m=rss",
          "ty": "press",
          "linkKind": "article"
        }
      ]
    },
    {
      "headline": "新給付制度、支援漏れ防止を検討　高市首相、集中審議に出席",
      "slug": "新給付制度支援漏れ防止を検討高市首相集中審議に出",
      "time": "2026-07-17T09:24:00.000Z",
      "independentSources": 1,
      "sources": [
        "時事ドットコム"
      ],
      "count": 1,
      "hasPrimary": false,
      "members": [
        {
          "title": "新給付制度、支援漏れ防止を検討　高市首相、集中審議に出席",
          "snippet": "",
          "source": "時事ドットコム",
          "link": "https://www.jiji.com/jc/article?k=2026071700129&g=pol&m=rss",
          "ty": "press",
          "linkKind": "article"
        }
      ]
    },
    {
      "headline": "二階堂有希子さん死去　声優",
      "slug": "二階堂有希子さん死去声優",
      "time": "2026-07-17T09:12:00.000Z",
      "independentSources": 1,
      "sources": [
        "時事ドットコム"
      ],
      "count": 1,
      "hasPrimary": false,
      "members": [
        {
          "title": "二階堂有希子さん死去　声優",
          "snippet": "",
          "source": "時事ドットコム",
          "link": "https://www.jiji.com/jc/article?k=2026071701020&g=soc&m=rss",
          "ty": "press",
          "linkKind": "article"
        }
      ]
    },
    {
      "headline": "中道の小川代表「世論に耳傾ける」　合流賛成１割に言及",
      "slug": "中道の小川代表世論に耳傾ける合流賛成割に言及",
      "time": "2026-07-17T07:16:00.000Z",
      "independentSources": 1,
      "sources": [
        "時事ドットコム"
      ],
      "count": 1,
      "hasPrimary": false,
      "members": [
        {
          "title": "中道の小川代表「世論に耳傾ける」　合流賛成１割に言及",
          "snippet": "",
          "source": "時事ドットコム",
          "link": "https://www.jiji.com/jc/article?k=2026071700862&g=pol&m=rss",
          "ty": "press",
          "linkKind": "article"
        }
      ]
    },
    {
      "headline": "典範改正「議員９割賛成」　木原官房長官",
      "slug": "典範改正議員割賛成木原官房長官",
      "time": "2026-07-17T08:54:00.000Z",
      "independentSources": 1,
      "sources": [
        "時事ドットコム"
      ],
      "count": 1,
      "hasPrimary": false,
      "members": [
        {
          "title": "典範改正「議員９割賛成」　木原官房長官",
          "snippet": "",
          "source": "時事ドットコム",
          "link": "https://www.jiji.com/jc/article?k=2026071701004&g=pol&m=rss",
          "ty": "press",
          "linkKind": "article"
        }
      ]
    },
    {
      "headline": "当て逃げ容疑、県議を書類送検　通報せず立ち去る―高知県警",
      "slug": "当て逃げ容疑県議を書類送検通報せず立ち去る高知県",
      "time": "2026-07-17T07:22:00.000Z",
      "independentSources": 1,
      "sources": [
        "時事ドットコム"
      ],
      "count": 1,
      "hasPrimary": false,
      "members": [
        {
          "title": "当て逃げ容疑、県議を書類送検　通報せず立ち去る―高知県警",
          "snippet": "",
          "source": "時事ドットコム",
          "link": "https://www.jiji.com/jc/article?k=2026071700866&g=soc&m=rss",
          "ty": "press",
          "linkKind": "article"
        }
      ]
    },
    {
      "headline": "恐竜時代の哺乳類化石発見　現生種の祖先も―早大など",
      "slug": "恐竜時代の哺乳類化石発見現生種の祖先も早大など",
      "time": "2026-07-17T09:08:00.000Z",
      "independentSources": 1,
      "sources": [
        "時事ドットコム"
      ],
      "count": 1,
      "hasPrimary": false,
      "members": [
        {
          "title": "恐竜時代の哺乳類化石発見　現生種の祖先も―早大など",
          "snippet": "",
          "source": "時事ドットコム",
          "link": "https://www.jiji.com/jc/article?k=2026071701015&g=soc&m=rss",
          "ty": "press",
          "linkKind": "article"
        }
      ]
    },
    {
      "headline": "降灰予報（定時）",
      "slug": "降灰予報定時",
      "time": "2026-07-17T08:00:00.000Z",
      "independentSources": 1,
      "sources": [
        "気象庁 地震・火山"
      ],
      "count": 1,
      "hasPrimary": true,
      "members": [
        {
          "title": "降灰予報（定時）",
          "snippet": "【火山名　諏訪之瀬島　降灰予報（定時）】　現在、諏訪之瀬島は噴火警戒レベル２（火口周辺規制）です。諏訪之瀬島で噴火が発生した場合には、１７日２１時から２４時までは火口から東方向、１８日０９時から１２時までは火口から東方向に降灰が予想されます",
          "source": "気象庁 地震・火山",
          "link": "https://www.data.jma.go.jp/developer/xml/data/20260717080047_0_VFVO53_010000.xml",
          "ty": "prim",
          "linkKind": "data"
        }
      ]
    },
    {
      "headline": "降灰予報（定時）",
      "slug": "降灰予報定時",
      "time": "2026-07-17T08:00:00.000Z",
      "independentSources": 1,
      "sources": [
        "気象庁 地震・火山"
      ],
      "count": 1,
      "hasPrimary": true,
      "members": [
        {
          "title": "降灰予報（定時）",
          "snippet": "【火山名　霧島山（新燃岳）　降灰予報（定時）】　現在、霧島山（新燃岳）は噴火警戒レベル２（火口周辺規制）です。霧島山（新燃岳）で噴火が発生した場合には、１７日２１時から２４時までは火口から東方向、１８日０９時から１２時までは火口から北東方向",
          "source": "気象庁 地震・火山",
          "link": "https://www.data.jma.go.jp/developer/xml/data/20260717080051_0_VFVO53_010000.xml",
          "ty": "prim",
          "linkKind": "data"
        }
      ]
    },
    {
      "headline": "降灰予報（定時）",
      "slug": "降灰予報定時",
      "time": "2026-07-17T08:00:00.000Z",
      "independentSources": 1,
      "sources": [
        "気象庁 地震・火山"
      ],
      "count": 1,
      "hasPrimary": true,
      "members": [
        {
          "title": "降灰予報（定時）",
          "snippet": "【火山名　雌阿寒岳　降灰予報（定時）】　現在、雌阿寒岳は噴火警戒レベル２（火口周辺規制）です。雌阿寒岳で噴火が発生した場合には、１７日２１時から２４時までは火口から北方向、１８日０９時から１２時までは火口から北方向に降灰が予想されます。",
          "source": "気象庁 地震・火山",
          "link": "https://www.data.jma.go.jp/developer/xml/data/20260717080030_0_VFVO53_010000.xml",
          "ty": "prim",
          "linkKind": "data"
        }
      ]
    },
    {
      "headline": "降灰予報（定時）",
      "slug": "降灰予報定時",
      "time": "2026-07-17T08:00:00.000Z",
      "independentSources": 1,
      "sources": [
        "気象庁 地震・火山"
      ],
      "count": 1,
      "hasPrimary": true,
      "members": [
        {
          "title": "降灰予報（定時）",
          "snippet": "【火山名　岩手山　降灰予報（定時）】　現在、岩手山は噴火警戒レベル２（火口周辺規制）です。岩手山で噴火が発生した場合には、１７日２１時から２４時までは火口から北方向、１８日０９時から１２時までは火口から北方向に降灰が予想されます。",
          "source": "気象庁 地震・火山",
          "link": "https://www.data.jma.go.jp/developer/xml/data/20260717080033_0_VFVO53_010000.xml",
          "ty": "prim",
          "linkKind": "data"
        }
      ]
    },
    {
      "headline": "降灰予報（定時）",
      "slug": "降灰予報定時",
      "time": "2026-07-17T08:00:00.000Z",
      "independentSources": 1,
      "sources": [
        "気象庁 地震・火山"
      ],
      "count": 1,
      "hasPrimary": true,
      "members": [
        {
          "title": "降灰予報（定時）",
          "snippet": "【火山名　阿蘇山　降灰予報（定時）】　現在、阿蘇山は噴火警戒レベル２（火口周辺規制）です。阿蘇山で噴火が発生した場合には、１７日２１時から２４時までは火口から北東方向、１８日０９時から１２時までは火口から北東方向に降灰が予想されます。",
          "source": "気象庁 地震・火山",
          "link": "https://www.data.jma.go.jp/developer/xml/data/20260717080036_0_VFVO53_010000.xml",
          "ty": "prim",
          "linkKind": "data"
        }
      ]
    },
    {
      "headline": "降灰予報（定時）",
      "slug": "降灰予報定時",
      "time": "2026-07-17T08:00:00.000Z",
      "independentSources": 1,
      "sources": [
        "気象庁 地震・火山"
      ],
      "count": 1,
      "hasPrimary": true,
      "members": [
        {
          "title": "降灰予報（定時）",
          "snippet": "【火山名　桜島　降灰予報（定時）】　現在、桜島は噴火警戒レベル３（入山規制）です。桜島で噴火が発生した場合には、１７日２１時から２４時までは火口から南東方向、１８日０９時から１２時までは火口から東方向に降灰が予想されます。",
          "source": "気象庁 地震・火山",
          "link": "https://www.data.jma.go.jp/developer/xml/data/20260717080040_0_VFVO53_010000.xml",
          "ty": "prim",
          "linkKind": "data"
        }
      ]
    },
    {
      "headline": "降灰予報（定時）",
      "slug": "降灰予報定時",
      "time": "2026-07-17T08:00:00.000Z",
      "independentSources": 1,
      "sources": [
        "気象庁 地震・火山"
      ],
      "count": 1,
      "hasPrimary": true,
      "members": [
        {
          "title": "降灰予報（定時）",
          "snippet": "【火山名　薩摩硫黄島　降灰予報（定時）】　現在、薩摩硫黄島は噴火警戒レベル２（火口周辺規制）です。薩摩硫黄島で噴火が発生した場合には、１７日２１時から２４時までは火口から東方向、１８日０９時から１２時までは火口から東方向に降灰が予想されます",
          "source": "気象庁 地震・火山",
          "link": "https://www.data.jma.go.jp/developer/xml/data/20260717080044_0_VFVO53_010000.xml",
          "ty": "prim",
          "linkKind": "data"
        }
      ]
    },
    {
      "headline": "火山の状況に関する解説情報",
      "slug": "火山の状況に関する解説情報",
      "time": "2026-07-17T07:04:09.000Z",
      "independentSources": 1,
      "sources": [
        "気象庁 地震・火山"
      ],
      "count": 1,
      "hasPrimary": true,
      "members": [
        {
          "title": "火山の状況に関する解説情報",
          "snippet": "【火山名  阿蘇山  火山の状況に関する解説情報】＜火口周辺警報（噴火警戒レベル２、火口周辺規制）が継続＞\n　７月１０日から１７日１５時までの阿蘇山の活動状況をお知らせします。\n　阿蘇山では、火山活動が高まっていることから、中岳第一火口から",
          "source": "気象庁 地震・火山",
          "link": "https://www.data.jma.go.jp/developer/xml/data/20260717070409_0_VFVO51_400000.xml",
          "ty": "prim",
          "linkKind": "data"
        }
      ]
    },
    {
      "headline": "火山の状況に関する解説情報",
      "slug": "火山の状況に関する解説情報",
      "time": "2026-07-17T07:03:12.000Z",
      "independentSources": 1,
      "sources": [
        "気象庁 地震・火山"
      ],
      "count": 1,
      "hasPrimary": true,
      "members": [
        {
          "title": "火山の状況に関する解説情報",
          "snippet": "【火山名  諏訪之瀬島  火山の状況に関する解説情報】＜火口周辺警報（噴火警戒レベル２、火口周辺規制）が継続＞\n　７月１０日から１７日１５時までの諏訪之瀬島の活動状況をお知らせします。",
          "source": "気象庁 地震・火山",
          "link": "https://www.data.jma.go.jp/developer/xml/data/20260717070312_0_VFVO51_400000.xml",
          "ty": "prim",
          "linkKind": "data"
        }
      ]
    },
    {
      "headline": "火山の状況に関する解説情報",
      "slug": "火山の状況に関する解説情報",
      "time": "2026-07-17T07:02:23.000Z",
      "independentSources": 1,
      "sources": [
        "気象庁 地震・火山"
      ],
      "count": 1,
      "hasPrimary": true,
      "members": [
        {
          "title": "火山の状況に関する解説情報",
          "snippet": "【火山名  薩摩硫黄島  火山の状況に関する解説情報】＜火口周辺警報（噴火警戒レベル２、火口周辺規制）が継続＞\n　７月１０日から１７日１５時までの薩摩硫黄島の活動状況をお知らせします。",
          "source": "気象庁 地震・火山",
          "link": "https://www.data.jma.go.jp/developer/xml/data/20260717070223_0_VFVO51_400000.xml",
          "ty": "prim",
          "linkKind": "data"
        }
      ]
    },
    {
      "headline": "気象警報・注意報（Ｒ０６）（その他注意報）",
      "slug": "気象警報注意報その他注意報",
      "time": "2026-07-17T10:33:53.000Z",
      "independentSources": 1,
      "sources": [
        "気象庁 気象警報・注意報"
      ],
      "count": 1,
      "hasPrimary": true,
      "members": [
        {
          "title": "気象警報・注意報（Ｒ０６）（その他注意報）",
          "snippet": "【青森県雷・濃霧注意報】青森県では、濃霧による視程障害に注意してください。",
          "source": "気象庁 気象警報・注意報",
          "link": "https://www.data.jma.go.jp/developer/xml/data/20260717103354_0_VPWW61_020000.xml",
          "ty": "prim",
          "linkKind": "data"
        }
      ]
    },
    {
      "headline": "気象警報・注意報（Ｒ０６）（大雨）",
      "slug": "気象警報注意報大雨",
      "time": "2026-07-17T10:31:21.000Z",
      "independentSources": 1,
      "sources": [
        "気象庁 気象警報・注意報"
      ],
      "count": 1,
      "hasPrimary": true,
      "members": [
        {
          "title": "気象警報・注意報（Ｒ０６）（大雨）",
          "snippet": "【茨城県大雨警報・注意報】南部では、低い土地の浸水や河川の増水に注意してください。",
          "source": "気象庁 気象警報・注意報",
          "link": "https://www.data.jma.go.jp/developer/xml/data/20260717103121_0_VPWW55_080000.xml",
          "ty": "prim",
          "linkKind": "data"
        }
      ]
    },
    {
      "headline": "More than 500 Rohingya vanished at sea - what happened?",
      "slug": "Morethan500Rohingyavanis",
      "time": "2026-07-17T03:07:11.000Z",
      "independentSources": 1,
      "sources": [
        "BBC World"
      ],
      "count": 1,
      "hasPrimary": false,
      "members": [
        {
          "title": "More than 500 Rohingya vanished at sea - what happened?",
          "snippet": "Two boats carrying an estimated 530 Rohingyas have disappeared since leaving Myanmar on 29 June.",
          "source": "BBC World",
          "link": "https://www.bbc.co.uk/news/articles/cr59n096mrmo?at_medium=RSS&at_campaign=rss",
          "ty": "press",
          "linkKind": "article"
        }
      ]
    },
    {
      "headline": "Japan relaxes royal succession rules - but ban on female emperors remains",
      "slug": "Japanrelaxesroyalsuccess",
      "time": "2026-07-17T05:16:34.000Z",
      "independentSources": 1,
      "sources": [
        "BBC World"
      ],
      "count": 1,
      "hasPrimary": false,
      "members": [
        {
          "title": "Japan relaxes royal succession rules - but ban on female emperors remains",
          "snippet": "The law now allows the adoption of male distant relatives aged over 15 back into the imperial family.",
          "source": "BBC World",
          "link": "https://www.bbc.co.uk/news/articles/cy07rz79zg9o?at_medium=RSS&at_campaign=rss",
          "ty": "press",
          "linkKind": "article"
        }
      ]
    },
    {
      "headline": "Philippines condemns monkey video on Chinese media as racist",
      "slug": "Philippinescondemnsmonke",
      "time": "2026-07-17T02:37:45.000Z",
      "independentSources": 1,
      "sources": [
        "BBC World"
      ],
      "count": 1,
      "hasPrimary": false,
      "members": [
        {
          "title": "Philippines condemns monkey video on Chinese media as racist",
          "snippet": "The AI video on China Daily showed a monkey in Philippine garments singing its claims to the South China Sea.",
          "source": "BBC World",
          "link": "https://www.bbc.co.uk/news/articles/cj632307934o?at_medium=RSS&at_campaign=rss",
          "ty": "press",
          "linkKind": "article"
        }
      ]
    },
    {
      "headline": "Trump Media to sell instant access to 'market-moving' social posts",
      "slug": "TrumpMediatosellinstanta",
      "time": "2026-07-17T07:25:31.000Z",
      "independentSources": 1,
      "sources": [
        "BBC World"
      ],
      "count": 1,
      "hasPrimary": false,
      "members": [
        {
          "title": "Trump Media to sell instant access to 'market-moving' social posts",
          "snippet": "Trump Media is launching a fast, paid feed to its most influential posts for Wall Street traders.",
          "source": "BBC World",
          "link": "https://www.bbc.co.uk/news/articles/c79gw4lj89eo?at_medium=RSS&at_campaign=rss",
          "ty": "press",
          "linkKind": "article"
        }
      ]
    },
    {
      "headline": "School bus crash kills at least 20 pupils in Uganda",
      "slug": "Schoolbuscrashkillsatlea",
      "time": "2026-07-17T10:04:27.000Z",
      "independentSources": 1,
      "sources": [
        "BBC World"
      ],
      "count": 1,
      "hasPrimary": false,
      "members": [
        {
          "title": "School bus crash kills at least 20 pupils in Uganda",
          "snippet": "Dozens others, including school staff, were injured in the crash, suspected to have been caused by a mechanical fault.",
          "source": "BBC World",
          "link": "https://www.bbc.co.uk/news/articles/c151gegwqv1o?at_medium=RSS&at_campaign=rss",
          "ty": "press",
          "linkKind": "article"
        }
      ]
    },
    {
      "headline": "Canada fires prompt US air quality alerts as smoke blankets major cities",
      "slug": "CanadafirespromptUSairqu",
      "time": "2026-07-17T02:15:23.000Z",
      "independentSources": 1,
      "sources": [
        "BBC World"
      ],
      "count": 1,
      "hasPrimary": false,
      "members": [
        {
          "title": "Canada fires prompt US air quality alerts as smoke blankets major cities",
          "snippet": "Smoke from more than 800 blazes has filled major cities from Toronto and New York, to parts of the US Midwest and Great ",
          "source": "BBC World",
          "link": "https://www.bbc.co.uk/news/articles/c0m7n427xd8o?at_medium=RSS&at_campaign=rss",
          "ty": "press",
          "linkKind": "article"
        }
      ]
    },
    {
      "headline": "China hits out at British Steel nationalisation",
      "slug": "ChinahitsoutatBritishSte",
      "time": "2026-07-17T08:25:55.000Z",
      "independentSources": 1,
      "sources": [
        "BBC World"
      ],
      "count": 1,
      "hasPrimary": false,
      "members": [
        {
          "title": "China hits out at British Steel nationalisation",
          "snippet": "The UK government said taking the firm into public hands would safeguard \"a vital national capability\".",
          "source": "BBC World",
          "link": "https://www.bbc.co.uk/news/articles/cjd4kvxpd3do?at_medium=RSS&at_campaign=rss",
          "ty": "press",
          "linkKind": "article"
        }
      ]
    },
    {
      "headline": "Olympic cyclist admits to driving despite ban after crash that killed wife",
      "slug": "Olympiccyclistadmitstodr",
      "time": "2026-07-17T05:09:14.000Z",
      "independentSources": 1,
      "sources": [
        "BBC World"
      ],
      "count": 1,
      "hasPrimary": false,
      "members": [
        {
          "title": "Olympic cyclist admits to driving despite ban after crash that killed wife",
          "snippet": "Rohan Dennis pleaded guilty to driving while disqualified after police pulled him over last month.",
          "source": "BBC World",
          "link": "https://www.bbc.co.uk/news/articles/c62q3ywep1ro?at_medium=RSS&at_campaign=rss",
          "ty": "press",
          "linkKind": "article"
        }
      ]
    },
    {
      "headline": "India debuts hydrogen-powered train as part of sustainability drive",
      "slug": "Indiadebutshydrogenpower",
      "time": "2026-07-17T10:25:08.000Z",
      "independentSources": 1,
      "sources": [
        "Al Jazeera"
      ],
      "count": 1,
      "hasPrimary": false,
      "members": [
        {
          "title": "India debuts hydrogen-powered train as part of sustainability drive",
          "snippet": "India joins a handful of countries that have successfully deployed the zero-emission technology in their rail networks.",
          "source": "Al Jazeera",
          "link": "https://www.aljazeera.com/economy/2026/7/17/india-debuts-hydrogen-powered-train-as-part-of-sustainability-drive?traffic_source=rss",
          "ty": "press",
          "linkKind": "article"
        }
      ]
    },
    {
      "headline": "World Cup third-place playoff: What are France and England playing for?",
      "slug": "WorldCupthirdplaceplayof",
      "time": "2026-07-17T10:15:48.000Z",
      "independentSources": 1,
      "sources": [
        "Al Jazeera"
      ],
      "count": 1,
      "hasPrimary": false,
      "members": [
        {
          "title": "World Cup third-place playoff: What are France and England playing for?",
          "snippet": "Didier Deschamps takes charge ⁠of Les Bleus for the final time while Kylian Mbappe is chasing individual history.",
          "source": "Al Jazeera",
          "link": "https://www.aljazeera.com/sports/2026/7/17/world-cup-third-place-playoff-what-are-france-and-england-playing-for?traffic_source=rss",
          "ty": "press",
          "linkKind": "article"
        }
      ]
    },
    {
      "headline": "Has Ukraine’s Zelenskyy created a rival by sacking his defence minister?",
      "slug": "HasUkrainesZelenskyycrea",
      "time": "2026-07-17T10:07:11.000Z",
      "independentSources": 1,
      "sources": [
        "Al Jazeera"
      ],
      "count": 1,
      "hasPrimary": false,
      "members": [
        {
          "title": "Has Ukraine’s Zelenskyy created a rival by sacking his defence minister?",
          "snippet": "Rallies in support of sacked Defence Minister Mykhailo Fedorov have exposed a political challenge for Zelenskyy.",
          "source": "Al Jazeera",
          "link": "https://www.aljazeera.com/news/2026/7/17/has-ukraines-zelenskyy-created-a-rival-by-sacking-his-defence-minister?traffic_source=rss",
          "ty": "press",
          "linkKind": "article"
        }
      ]
    },
    {
      "headline": "As Chinese economy slows, experts say there will be ‘problems for Beijing’",
      "slug": "AsChineseeconomyslowsexp",
      "time": "2026-07-17T10:06:25.000Z",
      "independentSources": 1,
      "sources": [
        "Al Jazeera"
      ],
      "count": 1,
      "hasPrimary": false,
      "members": [
        {
          "title": "As Chinese economy slows, experts say there will be ‘problems for Beijing’",
          "snippet": "While the &#039;export engine is running very hot&#039;, jobs are lagging, squeezing spending in China.",
          "source": "Al Jazeera",
          "link": "https://www.aljazeera.com/economy/2026/7/17/as-chinese-economy-slows-experts-say-there-will-be-problems-for-beijing?traffic_source=rss",
          "ty": "press",
          "linkKind": "article"
        }
      ]
    },
    {
      "headline": "Germany repeats call for EU force to replace UN peacekeepers in Lebanon",
      "slug": "GermanyrepeatscallforEUf",
      "time": "2026-07-17T09:24:03.000Z",
      "independentSources": 1,
      "sources": [
        "Al Jazeera"
      ],
      "count": 1,
      "hasPrimary": false,
      "members": [
        {
          "title": "Germany repeats call for EU force to replace UN peacekeepers in Lebanon",
          "snippet": "Berlin warns against a &#039;security vacuum&#039; in Lebanon&#039;s south once UNIFIL mandate expires at year&#039;s en",
          "source": "Al Jazeera",
          "link": "https://www.aljazeera.com/news/2026/7/17/germany-repeats-call-for-eu-force-to-replace-un-peacekeepers-in-lebanon?traffic_source=rss",
          "ty": "press",
          "linkKind": "article"
        }
      ]
    }
  ]
}
