{
  "note": "中立見出し（ブラインド見出し）＝評価語を除いた事実の再表現・自前の言葉。既定表示に使い、原見出しは切替で見られる。",
  "headlines": {
    "中国艦艇が日本のEEZ内で機関銃射撃訓練実施 防衛省が確認": "中国艦艇が日本のEEZ内で機関銃射撃訓練実施",
    "「強い経済」へ経済財政運営を抜本転換 高市政権 初の骨太方針": "政府、経済財政運営を転換し「強い経済」目指す",
    "Trump slaps 50% tariffs on Canada and Carney vows to 'intensify' trade talks": "トランプ氏、カナダ製品に50%関税",
    "US launches fresh strikes on Iran, as Trump warns of retaliation for deaths of soldiers": "米、イランに新たな攻撃実施",
    "Yemen's Houthis announce 'maritime embargo' on Saudi Arabia": "イエメンのフーシ派、サウジへの海上封鎖を発表",
    "Tate brothers appear in US court for extradition proceedings": "テート兄弟、米裁判所で引き渡し手続き",
    "Notorious drug cartel leader Ismael Zambada sentenced to life in US prison": "麻薬カルテル幹部、米で終身刑",
    "Rare identical quadruplets born in Australia": "オーストラリアで四つ子誕生",
    "Ten killed as Russian attacks on merchant ships in Black Sea intensify": "ロシア、黒海で商船攻撃激化",
    "岐阜 愛知で40度超 あすも関東甲信や東海で「酷暑日」予想": "岐阜・愛知で40度超、あすも関東甲信・東海で猛暑日予想",
    "羽田空港 強盗未遂事件 1時間近く前から被害車両を尾行か": "羽田空港強盗未遂、被害車両を1時間前から尾行か",
    "米10日連続攻撃 イランはバーレーンの米関連施設を攻撃": "米軍施設への攻撃、イランがバーレーンで実行",
    "「産業動物獣医師」増やすには 農相と大学生らが対策話し合う": "産業動物獣医師増員へ、農相と大学生らが対策協議",
    "気象庁3か月予報 8月は「高温傾向」猛暑日多くなる可能性も": "気象庁、8月は高温傾向で猛暑日多くなると予報",
    "コメ価格下落基調続く 今後の鍵は": "コメ価格下落基調、今後の動向が焦点",
    "金銭授受告白の県議 第三者委要望": "金銭授受告白の県議、第三者委設置を要望",
    "自民有志 トレカ振興の議連設立へ": "自民有志、トレカ振興の議連設立へ",
    "学習放獣したクマが出没 殺処分": "学習放獣のクマが出没、殺処分に",
    "独身偽装で結婚前提交際 賠償命令": "独身偽装結婚、賠償命令",
    "伐採中に倒れた木が直撃 男性死亡": "伐採中の倒木で男性死亡",
    "熱中症疑い死亡 発見時体温42.6℃": "熱中症疑い死亡、体温42.6℃",
    "今春センバツ4強 すでに3校が敗退": "今春センバツ4強のうち3校が敗退",
    "外交官全員の情報流出か　外務省傘下機関にサイバー攻撃―韓国": "韓国外務省傘下機関にサイバー攻撃、外交官情報流出か",
    "ロシア軍攻撃でインド船員４人死亡　外務省、代理大使呼び抗議": "ロシア軍攻撃でインド船員4人死亡、日本が抗議",
    "中国「国際法に合致」　日本ＥＥＺ内の訓練": "中国、日本EEZ内で訓練実施",
    "豪外相、中国海警を非難　フィリピン兵殴打「安定損ない、危険」": "豪外相、フィリピン兵殴打した中国海警を非難",
    "軍艦「長良」か、初の有人撮影　大戦中、魚雷受け沈没―熊本・天草沖": "大戦中の軍艦「長良」か、初の有人撮影",
    "福岡の蔵内県議長事務所に脅迫電話　容疑で６４歳男逮捕―県警": "福岡の県議長事務所に脅迫電話、男を逮捕",
    "「おしん」「はね駒」元ＮＨＫプロデューサー小林由紀子さん死去": "元NHKプロデューサー小林由紀子さん死去",
    "「副首都」、２２日参院審議入り　延長国会、駆け引き再開": "「副首都」構想、延長国会で審議入り",
    "カタール寄贈の新大統領専用機に安全上の懸念、トランプ氏「対策万全にする」": "カタール寄贈の新大統領専用機に安全懸念",
    "軍総司令官、前国防相と対立「知らず」　ウクライナ大統領、解任検討か": "ウクライナ大統領、軍総司令官と前国防相の対立で解任検討か",
    "Lebanese army says troops deploying in 'pilot zone' after Israeli withdrawal": "レバノン軍、イスラエル撤退後に兵士展開",
    "'Anti-ICE' army veteran started fire outside Manhattan federal building, say officials": "米退役軍人が連邦ビル放火か",
    "At least 27 dead and 83 missing after passenger ferry capsizes off Guyana": "ギアナ沖で旅客船転覆、27人死亡83人不明",
    "Arizona’s primary elections: Which US races to watch and why they matter": "アリゾナ州予備選、注目レースは",
    "Lebanon’s Joseph Aoun to meet Trump: What to expect": "レバノン軍総司令官、トランプ氏と会談へ",
    "FIFA World Cup: Who scored the most goals, assists, saves and yellow cards?": "サッカーW杯、最多得点者らは",
    "Can AI systems make moral decisions in war?": "AIは戦争で道徳的判断できるか",
    "Australian MP interrupts tough interview to yell at dog": "豪議員、インタビュー中に犬に叫ぶ",
    "Huge fire at Ukraine shopping centre after Russian drone strike": "ウクライナの商業施設、ロシアの攻撃で大規模火災",
    "Argentina deny World Cup villains’ role after Samuel Jackson-led slants": "アルゼンチン、W杯での悪役ぶりを否定",
    "Philippine Foreign Secretary says ASEAN must work together": "フィリピン外相、ASEANの協力訴え",
    "Hormuz tankers on fire, as US, Iran continue attacks: What’s the latest?": "ホルムズ海峡タンカー火災、米・イランの攻撃続く"
  }
}